test.py
passwordManagerByAscii/____wisdom.py
passwordManagerByAscii/__init__.py
passwordManagerByAscii/decoder.py
passwordManagerByAscii/encrypt.py
passwordManagerByAscii/generator.py
passwordManagerByAscii/validate.py
passwordManagerByAscii-0.2.3.dist-info/LICENSE
passwordManagerByAscii-0.2.3.dist-info/METADATA
passwordManagerByAscii-0.2.3.dist-info/WHEEL
passwordManagerByAscii-0.2.3.dist-info/entry_points.txt
passwordManagerByAscii-0.2.3.dist-info/top_level.txt
passwordManagerByAscii-0.2.3.dist-info/RECORD
