Metadata-Version: 2.1
Name: passwordManagerByAscii
Version: 0.2.3
Summary: A pacakge that can generate, validate, encode, and decode passwords. built with build using setuptools, uploaded to PyPI using twine, and distributed via pip.
Author-email: Victoria Zhang <rz1424@nyu.edu>, Tiffany Lee <el2765@nyu.edu>, Seok Tae Kim <stk319@nyu.edu>, Khalifa AlFalasi <ksa330@nyu.edu>, Jenny Shen <js10792@nyu.edu>
License: GNU GENERAL PUBLIC LICENSE
Project-URL: Homepage, https://github.com/software-students-fall2022/python-package-exercise-project-3-team-11
Project-URL: Repository, https://github.com/software-students-fall2022/python-package-exercise-project-3-team-11.git
Project-URL: Bug Tracker, https://github.com/software-students-fall2022/python-package-exercise-project-3-team-11/issues
Keywords: python,package,build,tutorial
Classifier: Programming Language :: Python :: 3
Classifier: Intended Audience :: Education
Classifier: License :: OSI Approved :: GNU General Public License v3 (GPLv3)
Classifier: Operating System :: OS Independent
Requires-Python: >=3.7
License-File: LICENSE
Provides-Extra: dev
Requires-Dist: pytest ; extra == 'dev'
